zclient/HelperModule.py
zclient/__init__.py
zclient/info.log
zclient/main.py
zserver/__init__.py
zserver/help.py
zserver/start.py
zserver/stop.py
zettasql-1.0.0.dist-info/LICENSE
zettasql-1.0.0.dist-info/METADATA
zettasql-1.0.0.dist-info/WHEEL
zettasql-1.0.0.dist-info/entry_points.txt
zettasql-1.0.0.dist-info/top_level.txt
zettasql-1.0.0.dist-info/RECORD
